athantime/__init__.py
athantime/calcs.py
athantime-1.0.0.dist-info/METADATA
athantime-1.0.0.dist-info/WHEEL
athantime-1.0.0.dist-info/entry_points.txt
athantime-1.0.0.dist-info/licenses/LICENSE
athantime-1.0.0.dist-info/RECORD
