Metadata-Version: 2.3
Name: athantime
Version: 1.0.0
Summary: Calculate and Generate Athan and Salah Times
Project-URL: Homepage, https://github.com/abunimeh/athantime
Project-URL: Documentation, https://github.com/abunimeh/athantime
Project-URL: Repository, https://github.com/abunimeh/athantime.git
Project-URL: Bug Tracker, https://github.com/abunimeh/athantime/issues
Project-URL: Changelog, https://github.com/me/spam/blob/master/CHANGELOG.md
Author-email: abunimeh <asd1815@gmail.com>
License-File: LICENSE
Requires-Python: >=3.10
